zktraffic/__init__.py
zktraffic/base/__init__.py
zktraffic/base/client_message.py
zktraffic/base/deque.py
zktraffic/base/network.py
zktraffic/base/process.py
zktraffic/base/server_message.py
zktraffic/base/sniffer.py
zktraffic/base/util.py
zktraffic/base/zookeeper.py
zktraffic/cli/__init__.py
zktraffic/cli/fle.py
zktraffic/cli/omni.py
zktraffic/cli/printer.py
zktraffic/cli/stats_daemon.py
zktraffic/cli/zab.py
zktraffic/cli/zk.py
zktraffic/endpoints/__init__.py
zktraffic/endpoints/endpoints_server.py
zktraffic/endpoints/stats_server.py
zktraffic/fle/__init__.py
zktraffic/fle/message.py
zktraffic/network/__init__.py
zktraffic/network/sniffer.py
zktraffic/omni/__init__.py
zktraffic/omni/omni_sniffer.py
zktraffic/stats/__init__.py
zktraffic/stats/accumulators.py
zktraffic/stats/loaders.py
zktraffic/stats/stats.py
zktraffic/stats/timer.py
zktraffic/stats/util.py
zktraffic/tests/__init__.py
zktraffic/tests/common.py
zktraffic/tests/test_accumulators.py
zktraffic/tests/test_cli.py
zktraffic/tests/test_fle_messages.py
zktraffic/tests/test_omni.py
zktraffic/tests/test_packets.py
zktraffic/tests/test_parse_config.py
zktraffic/tests/test_printer_fle.py
zktraffic/tests/test_printer_zab.py
zktraffic/tests/test_printers.py
zktraffic/tests/test_process_options.py
zktraffic/tests/test_sniffer.py
zktraffic/tests/test_stats_daemon.py
zktraffic/tests/test_util.py
zktraffic/tests/test_zab.py
zktraffic/zab/__init__.py
zktraffic/zab/quorum_packet.py
zktraffic-0.2.0.data/scripts/fle-dump
zktraffic-0.2.0.data/scripts/zab-dump
zktraffic-0.2.0.data/scripts/zk-dump
zktraffic-0.2.0.data/scripts/zk-omni-dump
zktraffic-0.2.0.data/scripts/zk-stats-daemon
zktraffic-0.2.0.dist-info/LICENSE
zktraffic-0.2.0.dist-info/METADATA
zktraffic-0.2.0.dist-info/WHEEL
zktraffic-0.2.0.dist-info/top_level.txt
zktraffic-0.2.0.dist-info/RECORD
