Metadata-Version: 2.1
Name: zktraffic
Version: 0.2.0
Summary: ZooKeeper protocol analyzer and stats gathering daemon
Home-page: https://github.com/twitter/zktraffic
Author: Raul Gutierrez Segales
Author-email: rgs@twitter.com
License: Apache
Keywords: ZooKeeper Sniffer Stats
Platform: UNKNOWN
Classifier: Development Status :: 3 - Alpha
Classifier: License :: OSI Approved :: Apache Software License
Classifier: Programming Language :: Python :: 2.7
Classifier: Programming Language :: Python :: 3.5
Classifier: Programming Language :: Python :: 3.6
Classifier: Programming Language :: Python :: 3.7
Classifier: Topic :: System :: Distributed Computing
Classifier: Topic :: System :: Networking
Requires-Dist: ansicolors
Requires-Dist: dpkt (==1.9.2)
Requires-Dist: hexdump
Requires-Dist: psutil (==5.6.1)
Requires-Dist: scapy (==2.4.2)
Requires-Dist: six (==1.12.0)
Requires-Dist: tabulate
Requires-Dist: twitter.common.app (==0.3.11)
Requires-Dist: twitter.common.collections (==0.3.11)
Requires-Dist: twitter.common.decorators (==0.3.11)
Requires-Dist: twitter.common.exceptions (==0.3.11)
Requires-Dist: twitter.common.http (==0.3.11)
Requires-Dist: twitter.common.log (==0.3.11)
Provides-Extra: test
Requires-Dist: dpkt (==1.9.2) ; extra == 'test'
Requires-Dist: mock ; extra == 'test'
Requires-Dist: nose ; extra == 'test'
Requires-Dist: twitter.common.log ; extra == 'test'
Requires-Dist: scapy (==2.4.2) ; extra == 'test'
Requires-Dist: six (==1.12.0) ; extra == 'test'
